analysis/AnalyzerLoader.py
analysis/FreeswitchAnalyzer.py
analysis/__init__.py
debug/Action.py
debug/Condition.py
debug/Context.py
debug/DebugRunner.py
debug/Extension.py
debug/Freeswitch.py
debug/FreeswitchConfigurationParser.py
debug/FreeswitchInstructionParser.py
debug/FreeswitchLoader.py
debug/MetaAction.py
debug/__init__.py
debug/modules/AbstractFreeswitchModule.py
debug/modules/__init__.py
debug/modules/acl/ModAcl.py
debug/modules/acl/ModAclList.py
debug/modules/acl/ModAclNode.py
debug/modules/acl/__init__.py
discovery/FileNode.py
discovery/FreeswitchFileDiscovery.py
discovery/__init__.py
formatters/__init__.py
formatters/console.py
formatters/json_formatter.py
frslint.py
lint/FreeswitchCodeStyleChecker.py
lint/__init__.py
log/Loggable.py
log/__init__.py
frslint-0.1.0.dist-info/METADATA
frslint-0.1.0.dist-info/WHEEL
frslint-0.1.0.dist-info/entry_points.txt
frslint-0.1.0.dist-info/RECORD
