Metadata-Version: 2.4
Name: frslint
Version: 0.1.0
Summary: Linter, static analyzer, dialplan evaluator for FreeSWITCH XML configuration files
License: MIT
Keywords: freeswitch,linter,xml,voip,telephony,configuration
Author: Yannick Zimmermann
Requires-Python: >=3.9
Classifier: Development Status :: 3 - Alpha
Classifier: Environment :: Console
Classifier: Intended Audience :: Developers
Classifier: Intended Audience :: System Administrators
Classifier: Intended Audience :: Telecommunications Industry
Classifier: License :: OSI Approved :: MIT License
Classifier: Operating System :: OS Independent
Classifier: Programming Language :: Python :: 3
Classifier: Programming Language :: Python :: 3.9
Classifier: Programming Language :: Python :: 3.10
Classifier: Programming Language :: Python :: 3.11
Classifier: Programming Language :: Python :: 3.12
Classifier: Programming Language :: Python :: 3.13
Classifier: Programming Language :: Python :: 3.14
Classifier: Topic :: Communications :: Telephony
Classifier: Topic :: Software Development :: Quality Assurance
Project-URL: Repository, https://github.com/zimmer-yan/frslint
